{
  "id": "4091664",
  "name": "VUE-portplay",
  "font_family": "iconfont",
  "css_prefix_text": "icon-",
  "description": "",
  "glyphs": [
    {
      "icon_id": "8289002",
      "name": "列表",
      "font_class": "liebiao",
      "unicode": "e86b",
      "unicode_decimal": 59499
    },
    {
      "icon_id": "1165",
      "name": "管理员",
      "font_class": "guanliyuan",
      "unicode": "e601",
      "unicode_decimal": 58881
    },
    {
      "icon_id": "1129591",
      "name": "密码",
      "font_class": "mima",
      "unicode": "e621",
      "unicode_decimal": 58913
    },
    {
      "icon_id": "2569869",
      "name": "登录",
      "font_class": "denglu",
      "unicode": "e67c",
      "unicode_decimal": 59004
    }
  ]
}
